atacama/__init__.py
atacama/client.py
atacama/exceptions.py
atacama-1.0.0.dist-info/METADATA
atacama-1.0.0.dist-info/WHEEL
atacama-1.0.0.dist-info/RECORD
